clockify/__init__.py
clockify/apis/client_api.py
clockify/apis/project_api.py
clockify/apis/tag_api.py
clockify/apis/task_api.py
clockify/apis/time_entry_api.py
clockify/apis/user.py
clockify/config.py
clockify/dto.py
clockify/mapper.py
clockify/model/__init__.py
clockify/model/base_model.py
clockify/model/client_model.py
clockify/model/project_model.py
clockify/model/tag_model.py
clockify/model/task_model.py
clockify/model/time_entry_model.py
clockify/model/user_model.py
clockify/session.py
clockify/wrapper.py
clockify_api-0.1.2.dist-info/WHEEL
clockify_api-0.1.2.dist-info/METADATA
clockify_api-0.1.2.dist-info/RECORD
